OCRUSREX/__init__.py
OCRUSREX/ocrusrex.py
OCRUSREX-0.2.2.dist-info/LICENSE
OCRUSREX-0.2.2.dist-info/METADATA
OCRUSREX-0.2.2.dist-info/WHEEL
OCRUSREX-0.2.2.dist-info/top_level.txt
OCRUSREX-0.2.2.dist-info/RECORD
