Metadata-Version: 2.1
Name: OCRUSREX
Version: 0.2.2
Summary: OCRUSREX takes a PDF (either by path or as a file-like object) and makes it searchable using Tesseract 4. It has an enterprise-friendly license.
Home-page: https://github.com/JSv4/OCRUSREX
Author: John Scrudato
Author-email: john@thelegal.engineer
License: UNKNOWN
Platform: UNKNOWN
Classifier: Programming Language :: Python :: 3
Classifier: License :: OSI Approved :: MIT License
Classifier: Operating System :: OS Independent
Requires-Python: >=3.6
Requires-Dist: pillow
Requires-Dist: pypdf2
Requires-Dist: pdf2image
Requires-Dist: pytesseract
Requires-Dist: multiprocess
Requires-Dist: python-Levenshtein
Requires-Dist: tika
